[
  {
    "계약월": "2025.03.",
    "계약일": "23",
    "층": "26",
    "매매가(만원)": 340000
  },
  {
    "계약월": "2025.03.",
    "계약일": "15",
    "층": "21",
    "매매가(만원)": 345000
  },
  {
    "계약월": "2025.02.",
    "계약일": "19",
    "층": "6",
    "매매가(만원)": 330000
  },
  {
    "계약월": "2025.02.",
    "계약일": "16",
    "층": "8",
    "매매가(만원)": 325000
  },
  {
    "계약월": "2025.02.",
    "계약일": "1",
    "층": "25",
    "매매가(만원)": 300000
  },
  {
    "계약월": "2025.01.",
    "계약일": "2",
    "층": "15",
    "매매가(만원)": 302000
  },
  {
    "계약월": "2024.12.",
    "계약일": "31",
    "층": "3",
    "매매가(만원)": 295000
  },
  {
    "계약월": "2024.12.",
    "계약일": "21",
    "층": "14",
    "매매가(만원)": 296600
  },
  {
    "계약월": "2024.12.",
    "계약일": "13",
    "층": "21",
    "매매가(만원)": 306000
  },
  {
    "계약월": "2024.11.",
    "계약일": "23",
    "층": "20",
    "매매가(만원)": 306000
  },
  {
    "계약월": "2024.11.",
    "계약일": "7",
    "층": "14",
    "매매가(만원)": 293000
  },
  {
    "계약월": "2024.10.",
    "계약일": "1",
    "층": "16",
    "매매가(만원)": 298000
  },
  {
    "계약월": "2024.09.",
    "계약일": "30",
    "층": "25",
    "매매가(만원)": 305000
  },
  {
    "계약월": "2024.09.",
    "계약일": "27",
    "층": "10",
    "매매가(만원)": 293000
  },
  {
    "계약월": "2024.09.",
    "계약일": "21",
    "층": "11",
    "매매가(만원)": 300000
  },
  {
    "계약월": "2024.08.",
    "계약일": "31",
    "층": "13",
    "매매가(만원)": 291000
  },
  {
    "계약월": "2024.07.",
    "계약일": "22",
    "층": "10",
    "매매가(만원)": 300000
  },
  {
    "계약월": "2024.07.",
    "계약일": "22",
    "층": "27",
    "매매가(만원)": 300000
  },
  {
    "계약월": "2024.07.",
    "계약일": "12",
    "층": "13",
    "매매가(만원)": 295000
  },
  {
    "계약월": "2024.07.",
    "계약일": "6",
    "층": "5",
    "매매가(만원)": 278000
  },
  {
    "계약월": "2024.07.",
    "계약일": "6",
    "층": "5",
    "매매가(만원)": 278000
  },
  {
    "계약월": "2024.07.",
    "계약일": "4",
    "층": "11",
    "매매가(만원)": 290000
  },
  {
    "계약월": "2024.06.",
    "계약일": "24",
    "층": "13",
    "매매가(만원)": 280000
  },
  {
    "계약월": "2024.05.",
    "계약일": "31",
    "층": "9",
    "매매가(만원)": 271000
  },
  {
    "계약월": "2024.05.",
    "계약일": "18",
    "층": "6",
    "매매가(만원)": 260000
  },
  {
    "계약월": "2024.05.",
    "계약일": "1",
    "층": "12",
    "매매가(만원)": 257000
  },
  {
    "계약월": "2024.04.",
    "계약일": "27",
    "층": "27",
    "매매가(만원)": 255000
  },
  {
    "계약월": "2024.04.",
    "계약일": "20",
    "층": "17",
    "매매가(만원)": 252000
  },
  {
    "계약월": "2024.04.",
    "계약일": "20",
    "층": "12",
    "매매가(만원)": 247000
  },
  {
    "계약월": "2024.03.",
    "계약일": "28",
    "층": "18",
    "매매가(만원)": 235000
  },
  {
    "계약월": "2024.03.",
    "계약일": "18",
    "층": "14",
    "매매가(만원)": 244000
  },
  {
    "계약월": "2024.03.",
    "계약일": "18",
    "층": "15",
    "매매가(만원)": 240000
  },
  {
    "계약월": "2024.03.",
    "계약일": "9",
    "층": "20",
    "매매가(만원)": 241500
  },
  {
    "계약월": "2024.03.",
    "계약일": "5",
    "층": "5",
    "매매가(만원)": 235000
  },
  {
    "계약월": "2024.01.",
    "계약일": "24",
    "층": "23",
    "매매가(만원)": 239000
  },
  {
    "계약월": "2024.01.",
    "계약일": "15",
    "층": "25",
    "매매가(만원)": 240000
  },
  {
    "계약월": "2024.01.",
    "계약일": "6",
    "층": "10",
    "매매가(만원)": 235000
  },
  {
    "계약월": "2024.01.",
    "계약일": "2",
    "층": "25",
    "매매가(만원)": 235000
  },
  {
    "계약월": "2023.09.",
    "계약일": "26",
    "층": "15",
    "매매가(만원)": 245000
  },
  {
    "계약월": "2023.09.",
    "계약일": "26",
    "층": "3",
    "매매가(만원)": 243500
  },
  {
    "계약월": "2023.09.",
    "계약일": "26",
    "층": "3",
    "매매가(만원)": 243500
  },
  {
    "계약월": "2023.09.",
    "계약일": "24",
    "층": "7",
    "매매가(만원)": 250000
  },
  {
    "계약월": "2023.08.",
    "계약일": "9",
    "층": "11",
    "매매가(만원)": 245000
  },
  {
    "계약월": "2023.07.",
    "계약일": "22",
    "층": "25",
    "매매가(만원)": 240000
  },
  {
    "계약월": "2023.07.",
    "계약일": "14",
    "층": "13",
    "매매가(만원)": 245500
  },
  {
    "계약월": "2023.06.",
    "계약일": "17",
    "층": "3",
    "매매가(만원)": 239000
  },
  {
    "계약월": "2023.06.",
    "계약일": "16",
    "층": "23",
    "매매가(만원)": 228000
  },
  {
    "계약월": "2023.06.",
    "계약일": "9",
    "층": "26",
    "매매가(만원)": 233000
  },
  {
    "계약월": "2023.06.",
    "계약일": "9",
    "층": "26",
    "매매가(만원)": 233000
  },
  {
    "계약월": "2023.05.",
    "계약일": "30",
    "층": "17",
    "매매가(만원)": 236000
  },
  {
    "계약월": "2023.05.",
    "계약일": "18",
    "층": "19",
    "매매가(만원)": 229000
  },
  {
    "계약월": "2023.04.",
    "계약일": "6",
    "층": "12",
    "매매가(만원)": 233000
  },
  {
    "계약월": "2023.03.",
    "계약일": "8",
    "층": "12",
    "매매가(만원)": 230000
  },
  {
    "계약월": "2023.01.",
    "계약일": "11",
    "층": "12",
    "매매가(만원)": 235000
  },
  {
    "계약월": "2022.05.",
    "계약일": "19",
    "층": "5",
    "매매가(만원)": 282000
  },
  {
    "계약월": "2021.12.",
    "계약일": "30",
    "층": "20",
    "매매가(만원)": 270000
  },
  {
    "계약월": "2021.09.",
    "계약일": "30",
    "층": "27",
    "매매가(만원)": 273000
  },
  {
    "계약월": "2021.09.",
    "계약일": "5",
    "층": "16",
    "매매가(만원)": 260000
  },
  {
    "계약월": "2021.07.",
    "계약일": "6",
    "층": "4",
    "매매가(만원)": 235000
  },
  {
    "계약월": "2021.05.",
    "계약일": "31",
    "층": "22",
    "매매가(만원)": 243500
  },
  {
    "계약월": "2021.04.",
    "계약일": "27",
    "층": "21",
    "매매가(만원)": 236000
  },
  {
    "계약월": "2021.03.",
    "계약일": "21",
    "층": "7",
    "매매가(만원)": 235000
  },
  {
    "계약월": "2021.02.",
    "계약일": "6",
    "층": "25",
    "매매가(만원)": 235000
  },
  {
    "계약월": "2021.01.",
    "계약일": "30",
    "층": "24",
    "매매가(만원)": 239000
  },
  {
    "계약월": "2020.12.",
    "계약일": "12",
    "층": "26",
    "매매가(만원)": 217000
  },
  {
    "계약월": "2020.12.",
    "계약일": "9",
    "층": "13",
    "매매가(만원)": 223000
  },
  {
    "계약월": "2020.07.",
    "계약일": "31",
    "층": "14",
    "매매가(만원)": 220000
  },
  {
    "계약월": "2020.07.",
    "계약일": "9",
    "층": "7",
    "매매가(만원)": 221000
  },
  {
    "계약월": "2020.06.",
    "계약일": "13",
    "층": "8",
    "매매가(만원)": 200000
  },
  {
    "계약월": "2020.05.",
    "계약일": "1",
    "층": "7",
    "매매가(만원)": 195000
  },
  {
    "계약월": "2020.02.",
    "계약일": "25",
    "층": "7",
    "매매가(만원)": 196000
  },
  {
    "계약월": "2020.01.",
    "계약일": "24",
    "층": "9",
    "매매가(만원)": 195000
  },
  {
    "계약월": "2019.12.",
    "계약일": "14",
    "층": "24",
    "매매가(만원)": 203000
  },
  {
    "계약월": "2019.12.",
    "계약일": "7",
    "층": "7",
    "매매가(만원)": 210000
  },
  {
    "계약월": "2019.11.",
    "계약일": "25",
    "층": "26",
    "매매가(만원)": 200000
  },
  {
    "계약월": "2019.11.",
    "계약일": "12",
    "층": "5",
    "매매가(만원)": 200000
  },
  {
    "계약월": "2019.11.",
    "계약일": "3",
    "층": "12",
    "매매가(만원)": 200000
  },
  {
    "계약월": "2019.10.",
    "계약일": "31",
    "층": "16",
    "매매가(만원)": 197000
  },
  {
    "계약월": "2019.10.",
    "계약일": "13",
    "층": "17",
    "매매가(만원)": 195000
  },
  {
    "계약월": "2019.10.",
    "계약일": "12",
    "층": "21",
    "매매가(만원)": 199000
  },
  {
    "계약월": "2019.10.",
    "계약일": "9",
    "층": "11",
    "매매가(만원)": 200000
  },
  {
    "계약월": "2019.10.",
    "계약일": "1",
    "층": "14",
    "매매가(만원)": 197000
  },
  {
    "계약월": "2019.09.",
    "계약일": "26",
    "층": "23",
    "매매가(만원)": 179500
  },
  {
    "계약월": "2019.09.",
    "계약일": "6",
    "층": "21",
    "매매가(만원)": 193500
  },
  {
    "계약월": "2019.08.",
    "계약일": "10",
    "층": "23",
    "매매가(만원)": 194500
  },
  {
    "계약월": "2019.07.",
    "계약일": "31",
    "층": "19",
    "매매가(만원)": 191000
  },
  {
    "계약월": "2019.07.",
    "계약일": "27",
    "층": "5",
    "매매가(만원)": 189200
  },
  {
    "계약월": "2019.07.",
    "계약일": "15",
    "층": "20",
    "매매가(만원)": 190000
  },
  {
    "계약월": "2019.07.",
    "계약일": "12",
    "층": "7",
    "매매가(만원)": 185000
  },
  {
    "계약월": "2019.07.",
    "계약일": "10",
    "층": "25",
    "매매가(만원)": 186000
  },
  {
    "계약월": "2019.07.",
    "계약일": "10",
    "층": "1",
    "매매가(만원)": 166000
  },
  {
    "계약월": "2019.07.",
    "계약일": "1",
    "층": "27",
    "매매가(만원)": 182000
  },
  {
    "계약월": "2019.06.",
    "계약일": "27",
    "층": "24",
    "매매가(만원)": 185000
  },
  {
    "계약월": "2019.06.",
    "계약일": "24",
    "층": "16",
    "매매가(만원)": 179000
  },
  {
    "계약월": "2019.06.",
    "계약일": "17",
    "층": "23",
    "매매가(만원)": 179500
  },
  {
    "계약월": "2019.05.",
    "계약일": "29",
    "층": "4",
    "매매가(만원)": 156500
  },
  {
    "계약월": "2019.05.",
    "계약일": "29",
    "층": "27",
    "매매가(만원)": 172000
  },
  {
    "계약월": "2019.05.",
    "계약일": "28",
    "층": "9",
    "매매가(만원)": 173000
  },
  {
    "계약월": "2019.05.",
    "계약일": "17",
    "층": "10",
    "매매가(만원)": 163000
  },
  {
    "계약월": "2019.05.",
    "계약일": "14",
    "층": "6",
    "매매가(만원)": 168000
  },
  {
    "계약월": "2019.05.",
    "계약일": "10",
    "층": "8",
    "매매가(만원)": 163000
  },
  {
    "계약월": "2019.05.",
    "계약일": "7",
    "층": "4",
    "매매가(만원)": 163000
  },
  {
    "계약월": "2019.04.",
    "계약일": "30",
    "층": "18",
    "매매가(만원)": 157000
  },
  {
    "계약월": "2019.04.",
    "계약일": "20",
    "층": "10",
    "매매가(만원)": 162000
  },
  {
    "계약월": "2019.04.",
    "계약일": "6",
    "층": "11",
    "매매가(만원)": 160000
  },
  {
    "계약월": "2019.03.",
    "계약일": "19",
    "층": "18",
    "매매가(만원)": 185000
  },
  {
    "계약월": "2019.02.",
    "계약일": "18",
    "층": "4",
    "매매가(만원)": 156500
  },
  {
    "계약월": "2018.12.",
    "계약일": "5",
    "층": "27",
    "매매가(만원)": 180000
  },
  {
    "계약월": "2018.11.",
    "계약일": "24",
    "층": "9",
    "매매가(만원)": 178000
  },
  {
    "계약월": "2018.09.",
    "계약일": "3",
    "층": "13",
    "매매가(만원)": 192000
  },
  {
    "계약월": "2018.08.",
    "계약일": "29",
    "층": "16",
    "매매가(만원)": 185000
  },
  {
    "계약월": "2018.08.",
    "계약일": "26",
    "층": "11",
    "매매가(만원)": 175000
  },
  {
    "계약월": "2018.08.",
    "계약일": "21",
    "층": "13",
    "매매가(만원)": 175000
  },
  {
    "계약월": "2018.08.",
    "계약일": "15",
    "층": "26",
    "매매가(만원)": 176000
  },
  {
    "계약월": "2018.08.",
    "계약일": "10",
    "층": "21",
    "매매가(만원)": 174600
  },
  {
    "계약월": "2018.01.",
    "계약일": "12",
    "층": "2",
    "매매가(만원)": 155000
  },
  {
    "계약월": "2018.01.",
    "계약일": "4",
    "층": "16",
    "매매가(만원)": 158000
  },
  {
    "계약월": "2017.12.",
    "계약일": "22",
    "층": "22",
    "매매가(만원)": 150000
  },
  {
    "계약월": "2017.12.",
    "계약일": "13",
    "층": "16",
    "매매가(만원)": 145000
  },
  {
    "계약월": "2017.10.",
    "계약일": "30",
    "층": "20",
    "매매가(만원)": 143500
  },
  {
    "계약월": "2017.10.",
    "계약일": "14",
    "층": "17",
    "매매가(만원)": 136000
  },
  {
    "계약월": "2017.09.",
    "계약일": "5",
    "층": "6",
    "매매가(만원)": 130000
  },
  {
    "계약월": "2017.07.",
    "계약일": "30",
    "층": "20",
    "매매가(만원)": 136000
  },
  {
    "계약월": "2017.07.",
    "계약일": "30",
    "층": "27",
    "매매가(만원)": 134500
  },
  {
    "계약월": "2017.07.",
    "계약일": "27",
    "층": "13",
    "매매가(만원)": 119500
  },
  {
    "계약월": "2017.07.",
    "계약일": "1",
    "층": "23",
    "매매가(만원)": 130000
  },
  {
    "계약월": "2017.06.",
    "계약일": "1",
    "층": "14",
    "매매가(만원)": 125000
  },
  {
    "계약월": "2017.05.",
    "계약일": "24",
    "층": "13",
    "매매가(만원)": 126000
  },
  {
    "계약월": "2017.05.",
    "계약일": "10",
    "층": "3",
    "매매가(만원)": 119900
  },
  {
    "계약월": "2017.04.",
    "계약일": "22",
    "층": "7",
    "매매가(만원)": 121000
  },
  {
    "계약월": "2017.04.",
    "계약일": "15",
    "층": "6",
    "매매가(만원)": 119600
  },
  {
    "계약월": "2017.03.",
    "계약일": "29",
    "층": "6",
    "매매가(만원)": 122000
  },
  {
    "계약월": "2017.02.",
    "계약일": "9",
    "층": "25",
    "매매가(만원)": 119000
  },
  {
    "계약월": "2017.02.",
    "계약일": "6",
    "층": "26",
    "매매가(만원)": 115000
  },
  {
    "계약월": "2017.01.",
    "계약일": "24",
    "층": "27",
    "매매가(만원)": 116000
  },
  {
    "계약월": "2017.01.",
    "계약일": "23",
    "층": "22",
    "매매가(만원)": 118000
  },
  {
    "계약월": "2016.10.",
    "계약일": "29",
    "층": "7",
    "매매가(만원)": 120000
  },
  {
    "계약월": "2016.10.",
    "계약일": "11",
    "층": "23",
    "매매가(만원)": 118000
  },
  {
    "계약월": "2016.10.",
    "계약일": "9",
    "층": "1",
    "매매가(만원)": 108000
  },
  {
    "계약월": "2016.09.",
    "계약일": "28",
    "층": "25",
    "매매가(만원)": 118000
  },
  {
    "계약월": "2016.09.",
    "계약일": "24",
    "층": "15",
    "매매가(만원)": 118000
  },
  {
    "계약월": "2016.08.",
    "계약일": "20",
    "층": "10",
    "매매가(만원)": 120000
  },
  {
    "계약월": "2016.08.",
    "계약일": "1",
    "층": "23",
    "매매가(만원)": 113500
  },
  {
    "계약월": "2016.07.",
    "계약일": "27",
    "층": "19",
    "매매가(만원)": 114500
  },
  {
    "계약월": "2016.06.",
    "계약일": "30",
    "층": "12",
    "매매가(만원)": 114800
  },
  {
    "계약월": "2016.06.",
    "계약일": "29",
    "층": "2",
    "매매가(만원)": 105000
  },
  {
    "계약월": "2016.06.",
    "계약일": "27",
    "층": "12",
    "매매가(만원)": 106000
  },
  {
    "계약월": "2016.06.",
    "계약일": "12",
    "층": "7",
    "매매가(만원)": 108000
  },
  {
    "계약월": "2016.05.",
    "계약일": "31",
    "층": "23",
    "매매가(만원)": 107000
  },
  {
    "계약월": "2016.05.",
    "계약일": "28",
    "층": "4",
    "매매가(만원)": 105000
  },
  {
    "계약월": "2016.05.",
    "계약일": "26",
    "층": "12",
    "매매가(만원)": 101000
  },
  {
    "계약월": "2016.05.",
    "계약일": "18",
    "층": "18",
    "매매가(만원)": 105000
  },
  {
    "계약월": "2016.05.",
    "계약일": "17",
    "층": "7",
    "매매가(만원)": 107000
  },
  {
    "계약월": "2016.05.",
    "계약일": "11",
    "층": "26",
    "매매가(만원)": 105500
  },
  {
    "계약월": "2016.05.",
    "계약일": "6",
    "층": "3",
    "매매가(만원)": 103000
  },
  {
    "계약월": "2016.04.",
    "계약일": "25",
    "층": "13",
    "매매가(만원)": 104500
  },
  {
    "계약월": "2016.04.",
    "계약일": "13",
    "층": "9",
    "매매가(만원)": 102000
  },
  {
    "계약월": "2016.03.",
    "계약일": "16",
    "층": "1",
    "매매가(만원)": 95000
  },
  {
    "계약월": "2016.03.",
    "계약일": "4",
    "층": "18",
    "매매가(만원)": 104300
  },
  {
    "계약월": "2016.02.",
    "계약일": "23",
    "층": "16",
    "매매가(만원)": 104000
  },
  {
    "계약월": "2016.02.",
    "계약일": "5",
    "층": "23",
    "매매가(만원)": 103800
  },
  {
    "계약월": "2016.01.",
    "계약일": "11",
    "층": "4",
    "매매가(만원)": 101000
  },
  {
    "계약월": "2016.01.",
    "계약일": "6",
    "층": "22",
    "매매가(만원)": 105500
  },
  {
    "계약월": "2015.12.",
    "계약일": "31",
    "층": "17",
    "매매가(만원)": 104000
  },
  {
    "계약월": "2015.11.",
    "계약일": "27",
    "층": "13",
    "매매가(만원)": 106000
  },
  {
    "계약월": "2015.11.",
    "계약일": "11",
    "층": "12",
    "매매가(만원)": 105000
  },
  {
    "계약월": "2015.10.",
    "계약일": "23",
    "층": "5",
    "매매가(만원)": 104850
  },
  {
    "계약월": "2015.10.",
    "계약일": "10",
    "층": "5",
    "매매가(만원)": 102500
  },
  {
    "계약월": "2015.10.",
    "계약일": "2",
    "층": "20",
    "매매가(만원)": 101750
  },
  {
    "계약월": "2015.09.",
    "계약일": "16",
    "층": "12",
    "매매가(만원)": 103000
  },
  {
    "계약월": "2015.09.",
    "계약일": "",
    "층": "",
    "매매가(만원)": 100000
  },
  {
    "계약월": "2015.06.",
    "계약일": "24",
    "층": "13",
    "매매가(만원)": 101000
  },
  {
    "계약월": "2015.06.",
    "계약일": "12",
    "층": "23",
    "매매가(만원)": 101000
  },
  {
    "계약월": "2015.06.",
    "계약일": "1",
    "층": "22",
    "매매가(만원)": 99500
  },
  {
    "계약월": "2015.05.",
    "계약일": "29",
    "층": "16",
    "매매가(만원)": 97500
  },
  {
    "계약월": "2015.05.",
    "계약일": "28",
    "층": "3",
    "매매가(만원)": 96000
  },
  {
    "계약월": "2015.04.",
    "계약일": "18",
    "층": "1",
    "매매가(만원)": 92000
  },
  {
    "계약월": "2015.04.",
    "계약일": "9",
    "층": "7",
    "매매가(만원)": 98000
  },
  {
    "계약월": "2015.03.",
    "계약일": "31",
    "층": "11",
    "매매가(만원)": 98000
  },
  {
    "계약월": "2015.03.",
    "계약일": "25",
    "층": "19",
    "매매가(만원)": 98000
  },
  {
    "계약월": "2015.03.",
    "계약일": "17",
    "층": "25",
    "매매가(만원)": 97920
  },
  {
    "계약월": "2015.03.",
    "계약일": "2",
    "층": "23",
    "매매가(만원)": 95000
  },
  {
    "계약월": "2015.02.",
    "계약일": "27",
    "층": "14",
    "매매가(만원)": 93500
  },
  {
    "계약월": "2015.02.",
    "계약일": "12",
    "층": "25",
    "매매가(만원)": 92500
  },
  {
    "계약월": "2015.02.",
    "계약일": "9",
    "층": "27",
    "매매가(만원)": 93300
  },
  {
    "계약월": "2015.01.",
    "계약일": "26",
    "층": "14",
    "매매가(만원)": 94000
  },
  {
    "계약월": "2015.01.",
    "계약일": "8",
    "층": "6",
    "매매가(만원)": 90000
  },
  {
    "계약월": "2014.12.",
    "계약일": "24",
    "층": "2",
    "매매가(만원)": 88500
  },
  {
    "계약월": "2014.12.",
    "계약일": "3",
    "층": "20",
    "매매가(만원)": 92400
  },
  {
    "계약월": "2014.12.",
    "계약일": "3",
    "층": "15",
    "매매가(만원)": 92000
  },
  {
    "계약월": "2014.11.",
    "계약일": "15",
    "층": "11",
    "매매가(만원)": 92000
  },
  {
    "계약월": "2014.11.",
    "계약일": "15",
    "층": "2",
    "매매가(만원)": 90000
  },
  {
    "계약월": "2014.11.",
    "계약일": "8",
    "층": "26",
    "매매가(만원)": 92200
  },
  {
    "계약월": "2014.11.",
    "계약일": "5",
    "층": "27",
    "매매가(만원)": 89800
  },
  {
    "계약월": "2014.10.",
    "계약일": "15",
    "층": "25",
    "매매가(만원)": 92000
  },
  {
    "계약월": "2014.10.",
    "계약일": "4",
    "층": "19",
    "매매가(만원)": 93000
  },
  {
    "계약월": "2014.10.",
    "계약일": "1",
    "층": "1",
    "매매가(만원)": 80000
  },
  {
    "계약월": "2014.09.",
    "계약일": "17",
    "층": "6",
    "매매가(만원)": 90000
  },
  {
    "계약월": "2014.09.",
    "계약일": "16",
    "층": "14",
    "매매가(만원)": 92000
  },
  {
    "계약월": "2014.08.",
    "계약일": "26",
    "층": "25",
    "매매가(만원)": 89900
  },
  {
    "계약월": "2014.07.",
    "계약일": "16",
    "층": "22",
    "매매가(만원)": 90000
  },
  {
    "계약월": "2014.06.",
    "계약일": "11",
    "층": "10",
    "매매가(만원)": 88500
  },
  {
    "계약월": "2014.06.",
    "계약일": "10",
    "층": "7",
    "매매가(만원)": 87000
  },
  {
    "계약월": "2014.05.",
    "계약일": "10",
    "층": "24",
    "매매가(만원)": 87000
  },
  {
    "계약월": "2014.05.",
    "계약일": "3",
    "층": "18",
    "매매가(만원)": 87500
  },
  {
    "계약월": "2014.04.",
    "계약일": "12",
    "층": "11",
    "매매가(만원)": 89000
  },
  {
    "계약월": "2014.04.",
    "계약일": "1",
    "층": "23",
    "매매가(만원)": 88000
  },
  {
    "계약월": "2014.03.",
    "계약일": "29",
    "층": "2",
    "매매가(만원)": 83000
  },
  {
    "계약월": "2014.03.",
    "계약일": "",
    "층": "",
    "매매가(만원)": 80000
  },
  {
    "계약월": "2014.03.",
    "계약일": "25",
    "층": "20",
    "매매가(만원)": 90000
  },
  {
    "계약월": "2014.03.",
    "계약일": "8",
    "층": "27",
    "매매가(만원)": 90000
  },
  {
    "계약월": "2014.03.",
    "계약일": "8",
    "층": "15",
    "매매가(만원)": 89000
  },
  {
    "계약월": "2014.03.",
    "계약일": "8",
    "층": "7",
    "매매가(만원)": 87800
  },
  {
    "계약월": "2014.03.",
    "계약일": "4",
    "층": "3",
    "매매가(만원)": 85000
  },
  {
    "계약월": "2014.02.",
    "계약일": "27",
    "층": "5",
    "매매가(만원)": 86500
  },
  {
    "계약월": "2014.02.",
    "계약일": "15",
    "층": "10",
    "매매가(만원)": 87000
  },
  {
    "계약월": "2014.02.",
    "계약일": "13",
    "층": "6",
    "매매가(만원)": 84900
  },
  {
    "계약월": "2014.02.",
    "계약일": "8",
    "층": "12",
    "매매가(만원)": 86000
  },
  {
    "계약월": "2014.02.",
    "계약일": "5",
    "층": "13",
    "매매가(만원)": 87500
  },
  {
    "계약월": "2014.01.",
    "계약일": "28",
    "층": "10",
    "매매가(만원)": 86700
  },
  {
    "계약월": "2014.01.",
    "계약일": "22",
    "층": "13",
    "매매가(만원)": 86800
  },
  {
    "계약월": "2014.01.",
    "계약일": "22",
    "층": "8",
    "매매가(만원)": 86500
  },
  {
    "계약월": "2014.01.",
    "계약일": "18",
    "층": "12",
    "매매가(만원)": 87500
  },
  {
    "계약월": "2014.01.",
    "계약일": "18",
    "층": "26",
    "매매가(만원)": 88000
  },
  {
    "계약월": "2014.01.",
    "계약일": "13",
    "층": "6",
    "매매가(만원)": 84900
  },
  {
    "계약월": "2014.01.",
    "계약일": "11",
    "층": "25",
    "매매가(만원)": 85650
  },
  {
    "계약월": "2014.01.",
    "계약일": "11",
    "층": "14",
    "매매가(만원)": 87500
  },
  {
    "계약월": "2014.01.",
    "계약일": "8",
    "층": "10",
    "매매가(만원)": 85000
  },
  {
    "계약월": "2013.12.",
    "계약일": "22",
    "층": "23",
    "매매가(만원)": 85650
  },
  {
    "계약월": "2013.12.",
    "계약일": "4",
    "층": "27",
    "매매가(만원)": 85300
  },
  {
    "계약월": "2013.11.",
    "계약일": "23",
    "층": "18",
    "매매가(만원)": 87000
  },
  {
    "계약월": "2013.11.",
    "계약일": "16",
    "층": "23",
    "매매가(만원)": 85000
  },
  {
    "계약월": "2013.10.",
    "계약일": "10",
    "층": "12",
    "매매가(만원)": 83000
  },
  {
    "계약월": "2013.10.",
    "계약일": "10",
    "층": "3",
    "매매가(만원)": 83400
  },
  {
    "계약월": "2013.10.",
    "계약일": "5",
    "층": "5",
    "매매가(만원)": 83000
  },
  {
    "계약월": "2013.10.",
    "계약일": "3",
    "층": "2",
    "매매가(만원)": 81700
  },
  {
    "계약월": "2013.09.",
    "계약일": "1",
    "층": "28",
    "매매가(만원)": 82000
  },
  {
    "계약월": "2013.08.",
    "계약일": "6",
    "층": "23",
    "매매가(만원)": 85000
  },
  {
    "계약월": "2013.06.",
    "계약일": "11",
    "층": "14",
    "매매가(만원)": 86900
  },
  {
    "계약월": "2013.05.",
    "계약일": "25",
    "층": "9",
    "매매가(만원)": 84600
  },
  {
    "계약월": "2013.05.",
    "계약일": "20",
    "층": "10",
    "매매가(만원)": 82000
  },
  {
    "계약월": "2013.05.",
    "계약일": "19",
    "층": "23",
    "매매가(만원)": 84500
  },
  {
    "계약월": "2013.05.",
    "계약일": "8",
    "층": "16",
    "매매가(만원)": 85000
  },
  {
    "계약월": "2013.04.",
    "계약일": "26",
    "층": "6",
    "매매가(만원)": 84000
  },
  {
    "계약월": "2013.04.",
    "계약일": "24",
    "층": "14",
    "매매가(만원)": 83700
  },
  {
    "계약월": "2013.04.",
    "계약일": "23",
    "층": "16",
    "매매가(만원)": 84000
  },
  {
    "계약월": "2013.04.",
    "계약일": "19",
    "층": "19",
    "매매가(만원)": 82500
  },
  {
    "계약월": "2013.04.",
    "계약일": "10",
    "층": "13",
    "매매가(만원)": 81700
  },
  {
    "계약월": "2013.03.",
    "계약일": "26",
    "층": "16",
    "매매가(만원)": 81000
  },
  {
    "계약월": "2013.03.",
    "계약일": "13",
    "층": "11",
    "매매가(만원)": 81500
  },
  {
    "계약월": "2013.03.",
    "계약일": "9",
    "층": "19",
    "매매가(만원)": 83000
  },
  {
    "계약월": "2013.03.",
    "계약일": "5",
    "층": "14",
    "매매가(만원)": 82500
  },
  {
    "계약월": "2013.02.",
    "계약일": "28",
    "층": "11",
    "매매가(만원)": 82800
  },
  {
    "계약월": "2013.02.",
    "계약일": "24",
    "층": "24",
    "매매가(만원)": 83000
  },
  {
    "계약월": "2013.02.",
    "계약일": "18",
    "층": "26",
    "매매가(만원)": 82800
  },
  {
    "계약월": "2013.02.",
    "계약일": "13",
    "층": "13",
    "매매가(만원)": 83300
  },
  {
    "계약월": "2012.12.",
    "계약일": "10",
    "층": "15",
    "매매가(만원)": 81000
  },
  {
    "계약월": "2012.12.",
    "계약일": "6",
    "층": "12",
    "매매가(만원)": 80000
  },
  {
    "계약월": "2012.12.",
    "계약일": "1",
    "층": "20",
    "매매가(만원)": 80000
  },
  {
    "계약월": "2012.11.",
    "계약일": "22",
    "층": "9",
    "매매가(만원)": 85000
  },
  {
    "계약월": "2012.11.",
    "계약일": "3",
    "층": "22",
    "매매가(만원)": 82000
  },
  {
    "계약월": "2012.09.",
    "계약일": "27",
    "층": "13",
    "매매가(만원)": 82700
  },
  {
    "계약월": "2012.06.",
    "계약일": "5",
    "층": "17",
    "매매가(만원)": 87400
  },
  {
    "계약월": "2012.02.",
    "계약일": "1",
    "층": "1",
    "매매가(만원)": 81000
  },
  {
    "계약월": "2012.01.",
    "계약일": "28",
    "층": "24",
    "매매가(만원)": 89500
  },
  {
    "계약월": "2011.12.",
    "계약일": "7",
    "층": "17",
    "매매가(만원)": 30000
  },
  {
    "계약월": "2011.11.",
    "계약일": "28",
    "층": "20",
    "매매가(만원)": 89500
  },
  {
    "계약월": "2011.08.",
    "계약일": "24",
    "층": "22",
    "매매가(만원)": 89950
  },
  {
    "계약월": "2011.07.",
    "계약일": "5",
    "층": "25",
    "매매가(만원)": 88500
  },
  {
    "계약월": "2011.06.",
    "계약일": "13",
    "층": "14",
    "매매가(만원)": 87500
  },
  {
    "계약월": "2011.05.",
    "계약일": "26",
    "층": "11",
    "매매가(만원)": 83000
  },
  {
    "계약월": "2011.04.",
    "계약일": "13",
    "층": "16",
    "매매가(만원)": 93000
  },
  {
    "계약월": "2011.04.",
    "계약일": "6",
    "층": "10",
    "매매가(만원)": 89000
  },
  {
    "계약월": "2011.04.",
    "계약일": "2",
    "층": "20",
    "매매가(만원)": 89000
  },
  {
    "계약월": "2011.03.",
    "계약일": "28",
    "층": "24",
    "매매가(만원)": 91500
  },
  {
    "계약월": "2011.02.",
    "계약일": "19",
    "층": "6",
    "매매가(만원)": 89500
  },
  {
    "계약월": "2011.01.",
    "계약일": "16",
    "층": "20",
    "매매가(만원)": 85500
  },
  {
    "계약월": "2011.01.",
    "계약일": "11",
    "층": "26",
    "매매가(만원)": 86500
  },
  {
    "계약월": "2011.01.",
    "계약일": "4",
    "층": "7",
    "매매가(만원)": 89500
  },
  {
    "계약월": "2010.12.",
    "계약일": "24",
    "층": "22",
    "매매가(만원)": 86500
  },
  {
    "계약월": "2010.12.",
    "계약일": "18",
    "층": "23",
    "매매가(만원)": 88400
  },
  {
    "계약월": "2010.12.",
    "계약일": "17",
    "층": "6",
    "매매가(만원)": 87500
  },
  {
    "계약월": "2010.12.",
    "계약일": "10",
    "층": "12",
    "매매가(만원)": 88000
  },
  {
    "계약월": "2010.12.",
    "계약일": "8",
    "층": "14",
    "매매가(만원)": 85500
  },
  {
    "계약월": "2010.12.",
    "계약일": "4",
    "층": "24",
    "매매가(만원)": 88000
  },
  {
    "계약월": "2010.11.",
    "계약일": "19",
    "층": "6",
    "매매가(만원)": 86500
  },
  {
    "계약월": "2010.11.",
    "계약일": "15",
    "층": "3",
    "매매가(만원)": 85500
  },
  {
    "계약월": "2010.10.",
    "계약일": "25",
    "층": "11",
    "매매가(만원)": 86900
  },
  {
    "계약월": "2010.10.",
    "계약일": "17",
    "층": "23",
    "매매가(만원)": 89300
  },
  {
    "계약월": "2010.09.",
    "계약일": "28",
    "층": "18",
    "매매가(만원)": 82500
  },
  {
    "계약월": "2010.04.",
    "계약일": "23",
    "층": "26",
    "매매가(만원)": 85000
  },
  {
    "계약월": "2010.03.",
    "계약일": "31",
    "층": "7",
    "매매가(만원)": 86500
  },
  {
    "계약월": "2010.03.",
    "계약일": "27",
    "층": "12",
    "매매가(만원)": 87000
  },
  {
    "계약월": "2010.03.",
    "계약일": "",
    "층": "",
    "매매가(만원)": 90000
  },
  {
    "계약월": "2010.02.",
    "계약일": "1",
    "층": "21",
    "매매가(만원)": 85000
  },
  {
    "계약월": "2010.01.",
    "계약일": "29",
    "층": "20",
    "매매가(만원)": 84000
  },
  {
    "계약월": "2010.01.",
    "계약일": "",
    "층": "",
    "매매가(만원)": 80000
  },
  {
    "계약월": "2010.01.",
    "계약일": "14",
    "층": "3",
    "매매가(만원)": 83000
  },
  {
    "계약월": "2009.12.",
    "계약일": "28",
    "층": "1",
    "매매가(만원)": 71600
  },
  {
    "계약월": "2009.12.",
    "계약일": "23",
    "층": "9",
    "매매가(만원)": 83000
  },
  {
    "계약월": "2009.12.",
    "계약일": "18",
    "층": "11",
    "매매가(만원)": 90000
  },
  {
    "계약월": "2009.12.",
    "계약일": "14",
    "층": "26",
    "매매가(만원)": 77600
  },
  {
    "계약월": "2009.12.",
    "계약일": "7",
    "층": "18",
    "매매가(만원)": 84000
  },
  {
    "계약월": "2009.12.",
    "계약일": "1",
    "층": "7",
    "매매가(만원)": 77600
  },
  {
    "계약월": "2009.11.",
    "계약일": "18",
    "층": "2",
    "매매가(만원)": 77000
  },
  {
    "계약월": "2009.10.",
    "계약일": "30",
    "층": "1",
    "매매가(만원)": 71200
  },
  {
    "계약월": "2009.10.",
    "계약일": "30",
    "층": "26",
    "매매가(만원)": 77600
  },
  {
    "계약월": "2009.10.",
    "계약일": "29",
    "층": "27",
    "매매가(만원)": 77200
  },
  {
    "계약월": "2009.10.",
    "계약일": "29",
    "층": "24",
    "매매가(만원)": 77200
  },
  {
    "계약월": "2009.10.",
    "계약일": "26",
    "층": "20",
    "매매가(만원)": 77600
  },
  {
    "계약월": "2009.10.",
    "계약일": "26",
    "층": "21",
    "매매가(만원)": 77200
  },
  {
    "계약월": "2009.10.",
    "계약일": "23",
    "층": "20",
    "매매가(만원)": 77200
  },
  {
    "계약월": "2009.10.",
    "계약일": "21",
    "층": "1",
    "매매가(만원)": 71200
  },
  {
    "계약월": "2009.10.",
    "계약일": "19",
    "층": "1",
    "매매가(만원)": 71200
  },
  {
    "계약월": "2009.10.",
    "계약일": "14",
    "층": "2",
    "매매가(만원)": 73400
  },
  {
    "계약월": "2009.10.",
    "계약일": "14",
    "층": "1",
    "매매가(만원)": 71200
  },
  {
    "계약월": "2009.10.",
    "계약일": "8",
    "층": "19",
    "매매가(만원)": 77600
  },
  {
    "계약월": "2009.10.",
    "계약일": "6",
    "층": "9",
    "매매가(만원)": 82000
  },
  {
    "계약월": "2009.10.",
    "계약일": "5",
    "층": "15",
    "매매가(만원)": 77600
  },
  {
    "계약월": "2009.09.",
    "계약일": "30",
    "층": "18",
    "매매가(만원)": 83000
  },
  {
    "계약월": "2009.09.",
    "계약일": "25",
    "층": "26",
    "매매가(만원)": 77600
  },
  {
    "계약월": "2009.09.",
    "계약일": "24",
    "층": "1",
    "매매가(만원)": 71200
  },
  {
    "계약월": "2009.09.",
    "계약일": "15",
    "층": "1",
    "매매가(만원)": 71600
  },
  {
    "계약월": "2009.09.",
    "계약일": "14",
    "층": "1",
    "매매가(만원)": 71600
  },
  {
    "계약월": "2009.09.",
    "계약일": "14",
    "층": "6",
    "매매가(만원)": 77600
  },
  {
    "계약월": "2009.09.",
    "계약일": "10",
    "층": "3",
    "매매가(만원)": 74900
  },
  {
    "계약월": "2009.09.",
    "계약일": "9",
    "층": "14",
    "매매가(만원)": 77600
  },
  {
    "계약월": "2009.09.",
    "계약일": "7",
    "층": "2",
    "매매가(만원)": 73400
  },
  {
    "계약월": "2009.09.",
    "계약일": "7",
    "층": "4",
    "매매가(만원)": 74900
  },
  {
    "계약월": "2009.09.",
    "계약일": "6",
    "층": "13",
    "매매가(만원)": 77600
  },
  {
    "계약월": "2009.09.",
    "계약일": "4",
    "층": "2",
    "매매가(만원)": 73800
  },
  {
    "계약월": "2009.09.",
    "계약일": "4",
    "층": "11",
    "매매가(만원)": 77600
  },
  {
    "계약월": "2009.09.",
    "계약일": "4",
    "층": "6",
    "매매가(만원)": 77600
  },
  {
    "계약월": "2009.09.",
    "계약일": "4",
    "층": "1",
    "매매가(만원)": 71600
  },
  {
    "계약월": "2009.09.",
    "계약일": "3",
    "층": "23",
    "매매가(만원)": 77200
  },
  {
    "계약월": "2009.09.",
    "계약일": "3",
    "층": "19",
    "매매가(만원)": 77600
  },
  {
    "계약월": "2009.09.",
    "계약일": "2",
    "층": "23",
    "매매가(만원)": 77200
  },
  {
    "계약월": "2009.09.",
    "계약일": "2",
    "층": "6",
    "매매가(만원)": 77200
  },
  {
    "계약월": "2009.09.",
    "계약일": "2",
    "층": "14",
    "매매가(만원)": 77600
  },
  {
    "계약월": "2009.09.",
    "계약일": "2",
    "층": "12",
    "매매가(만원)": 77600
  },
  {
    "계약월": "2009.09.",
    "계약일": "2",
    "층": "8",
    "매매가(만원)": 77600
  },
  {
    "계약월": "2009.09.",
    "계약일": "2",
    "층": "18",
    "매매가(만원)": 77600
  },
  {
    "계약월": "2009.09.",
    "계약일": "2",
    "층": "6",
    "매매가(만원)": 77600
  },
  {
    "계약월": "2009.09.",
    "계약일": "1",
    "층": "10",
    "매매가(만원)": 77600
  },
  {
    "계약월": "2009.09.",
    "계약일": "1",
    "층": "12",
    "매매가(만원)": 77200
  },
  {
    "계약월": "2009.09.",
    "계약일": "1",
    "층": "8",
    "매매가(만원)": 77600
  },
  {
    "계약월": "2009.09.",
    "계약일": "1",
    "층": "26",
    "매매가(만원)": 77600
  },
  {
    "계약월": "2009.08.",
    "계약일": "31",
    "층": "3",
    "매매가(만원)": 74900
  },
  {
    "계약월": "2009.08.",
    "계약일": "31",
    "층": "9",
    "매매가(만원)": 77200
  },
  {
    "계약월": "2009.08.",
    "계약일": "31",
    "층": "7",
    "매매가(만원)": 77200
  },
  {
    "계약월": "2009.08.",
    "계약일": "31",
    "층": "6",
    "매매가(만원)": 77200
  },
  {
    "계약월": "2009.08.",
    "계약일": "31",
    "층": "9",
    "매매가(만원)": 77600
  },
  {
    "계약월": "2009.08.",
    "계약일": "28",
    "층": "11",
    "매매가(만원)": 80000
  },
  {
    "계약월": "2009.08.",
    "계약일": "28",
    "층": "15",
    "매매가(만원)": 77200
  },
  {
    "계약월": "2009.08.",
    "계약일": "28",
    "층": "9",
    "매매가(만원)": 77600
  },
  {
    "계약월": "2009.08.",
    "계약일": "28",
    "층": "10",
    "매매가(만원)": 77200
  },
  {
    "계약월": "2009.08.",
    "계약일": "25",
    "층": "10",
    "매매가(만원)": 77600
  },
  {
    "계약월": "2009.08.",
    "계약일": "22",
    "층": "6",
    "매매가(만원)": 77600
  },
  {
    "계약월": "2009.08.",
    "계약일": "21",
    "층": "6",
    "매매가(만원)": 77600
  },
  {
    "계약월": "2009.08.",
    "계약일": "21",
    "층": "3",
    "매매가(만원)": 75300
  },
  {
    "계약월": "2009.08.",
    "계약일": "19",
    "층": "5",
    "매매가(만원)": 75300
  },
  {
    "계약월": "2009.08.",
    "계약일": "19",
    "층": "28",
    "매매가(만원)": 77600
  },
  {
    "계약월": "2009.08.",
    "계약일": "19",
    "층": "19",
    "매매가(만원)": 77600
  },
  {
    "계약월": "2009.08.",
    "계약일": "18",
    "층": "18",
    "매매가(만원)": 77200
  },
  {
    "계약월": "2009.08.",
    "계약일": "17",
    "층": "12",
    "매매가(만원)": 77600
  },
  {
    "계약월": "2009.08.",
    "계약일": "17",
    "층": "14",
    "매매가(만원)": 82500
  },
  {
    "계약월": "2009.08.",
    "계약일": "17",
    "층": "10",
    "매매가(만원)": 77600
  },
  {
    "계약월": "2009.08.",
    "계약일": "17",
    "층": "7",
    "매매가(만원)": 77600
  },
  {
    "계약월": "2009.08.",
    "계약일": "17",
    "층": "9",
    "매매가(만원)": 77600
  },
  {
    "계약월": "2009.08.",
    "계약일": "17",
    "층": "3",
    "매매가(만원)": 75300
  },
  {
    "계약월": "2009.08.",
    "계약일": "15",
    "층": "6",
    "매매가(만원)": 77600
  },
  {
    "계약월": "2009.08.",
    "계약일": "14",
    "층": "10",
    "매매가(만원)": 77600
  },
  {
    "계약월": "2009.08.",
    "계약일": "13",
    "층": "10",
    "매매가(만원)": 77600
  },
  {
    "계약월": "2009.08.",
    "계약일": "13",
    "층": "13",
    "매매가(만원)": 77600
  },
  {
    "계약월": "2009.08.",
    "계약일": "12",
    "층": "11",
    "매매가(만원)": 77600
  },
  {
    "계약월": "2009.08.",
    "계약일": "12",
    "층": "14",
    "매매가(만원)": 77200
  },
  {
    "계약월": "2009.08.",
    "계약일": "12",
    "층": "7",
    "매매가(만원)": 77600
  },
  {
    "계약월": "2009.08.",
    "계약일": "12",
    "층": "11",
    "매매가(만원)": 77200
  },
  {
    "계약월": "2009.08.",
    "계약일": "10",
    "층": "3",
    "매매가(만원)": 74900
  },
  {
    "계약월": "2009.08.",
    "계약일": "7",
    "층": "4",
    "매매가(만원)": 74900
  },
  {
    "계약월": "2009.08.",
    "계약일": "5",
    "층": "4",
    "매매가(만원)": 75300
  },
  {
    "계약월": "2009.08.",
    "계약일": "4",
    "층": "6",
    "매매가(만원)": 77200
  },
  {
    "계약월": "2009.08.",
    "계약일": "3",
    "층": "18",
    "매매가(만원)": 79300
  },
  {
    "계약월": "2009.07.",
    "계약일": "31",
    "층": "5",
    "매매가(만원)": 74900
  },
  {
    "계약월": "2009.07.",
    "계약일": "30",
    "층": "11",
    "매매가(만원)": 77600
  },
  {
    "계약월": "2009.07.",
    "계약일": "28",
    "층": "11",
    "매매가(만원)": 80000
  },
  {
    "계약월": "2009.07.",
    "계약일": "27",
    "층": "21",
    "매매가(만원)": 77145
  },
  {
    "계약월": "2009.07.",
    "계약일": "20",
    "층": "25",
    "매매가(만원)": 81000
  },
  {
    "계약월": "2009.07.",
    "계약일": "17",
    "층": "6",
    "매매가(만원)": 77200
  },
  {
    "계약월": "2009.07.",
    "계약일": "13",
    "층": "14",
    "매매가(만원)": 77600
  },
  {
    "계약월": "2009.07.",
    "계약일": "10",
    "층": "13",
    "매매가(만원)": 77600
  },
  {
    "계약월": "2009.07.",
    "계약일": "10",
    "층": "19",
    "매매가(만원)": 78500
  },
  {
    "계약월": "2009.07.",
    "계약일": "9",
    "층": "3",
    "매매가(만원)": 75300
  },
  {
    "계약월": "2009.07.",
    "계약일": "9",
    "층": "27",
    "매매가(만원)": 80000
  },
  {
    "계약월": "2009.07.",
    "계약일": "8",
    "층": "3",
    "매매가(만원)": 75300
  },
  {
    "계약월": "2009.07.",
    "계약일": "8",
    "층": "25",
    "매매가(만원)": 81000
  },
  {
    "계약월": "2009.07.",
    "계약일": "8",
    "층": "9",
    "매매가(만원)": 77600
  },
  {
    "계약월": "2009.07.",
    "계약일": "6",
    "층": "2",
    "매매가(만원)": 73800
  },
  {
    "계약월": "2009.07.",
    "계약일": "3",
    "층": "15",
    "매매가(만원)": 77600
  },
  {
    "계약월": "2009.07.",
    "계약일": "2",
    "층": "12",
    "매매가(만원)": 77600
  },
  {
    "계약월": "2009.06.",
    "계약일": "10",
    "층": "22",
    "매매가(만원)": 77532
  },
  {
    "계약월": "2009.06.",
    "계약일": "9",
    "층": "2",
    "매매가(만원)": 73721
  },
  {
    "계약월": "2009.06.",
    "계약일": "8",
    "층": "23",
    "매매가(만원)": 77145
  },
  {
    "계약월": "2009.06.",
    "계약일": "8",
    "층": "26",
    "매매가(만원)": 77300
  },
  {
    "계약월": "2009.06.",
    "계약일": "5",
    "층": "23",
    "매매가(만원)": 77532
  },
  {
    "계약월": "2009.06.",
    "계약일": "4",
    "층": "15",
    "매매가(만원)": 77532
  },
  {
    "계약월": "2009.06.",
    "계약일": "3",
    "층": "14",
    "매매가(만원)": 77145
  },
  {
    "계약월": "2009.05.",
    "계약일": "29",
    "층": "10",
    "매매가(만원)": 77532
  },
  {
    "계약월": "2009.05.",
    "계약일": "29",
    "층": "21",
    "매매가(만원)": 77145
  },
  {
    "계약월": "2009.05.",
    "계약일": "29",
    "층": "22",
    "매매가(만원)": 77532
  },
  {
    "계약월": "2009.05.",
    "계약일": "27",
    "층": "11",
    "매매가(만원)": 77532
  },
  {
    "계약월": "2009.05.",
    "계약일": "26",
    "층": "2",
    "매매가(만원)": 73721
  },
  {
    "계약월": "2009.05.",
    "계약일": "26",
    "층": "9",
    "매매가(만원)": 77532
  },
  {
    "계약월": "2009.05.",
    "계약일": "26",
    "층": "4",
    "매매가(만원)": 74850
  },
  {
    "계약월": "2009.05.",
    "계약일": "26",
    "층": "15",
    "매매가(만원)": 77145
  },
  {
    "계약월": "2009.05.",
    "계약일": "26",
    "층": "18",
    "매매가(만원)": 77145
  },
  {
    "계약월": "2009.05.",
    "계약일": "26",
    "층": "5",
    "매매가(만원)": 74850
  },
  {
    "계약월": "2009.05.",
    "계약일": "26",
    "층": "4",
    "매매가(만원)": 75225
  },
  {
    "계약월": "2009.05.",
    "계약일": "26",
    "층": "5",
    "매매가(만원)": 75225
  },
  {
    "계약월": "2009.05.",
    "계약일": "26",
    "층": "28",
    "매매가(만원)": 77532
  },
  {
    "계약월": "2009.05.",
    "계약일": "26",
    "층": "26",
    "매매가(만원)": 77532
  },
  {
    "계약월": "2009.05.",
    "계약일": "26",
    "층": "3",
    "매매가(만원)": 74850
  },
  {
    "계약월": "2009.05.",
    "계약일": "26",
    "층": "18",
    "매매가(만원)": 77532
  },
  {
    "계약월": "2009.05.",
    "계약일": "26",
    "층": "1",
    "매매가(만원)": 71514
  },
  {
    "계약월": "2009.05.",
    "계약일": "26",
    "층": "10",
    "매매가(만원)": 77145
  },
  {
    "계약월": "2009.05.",
    "계약일": "26",
    "층": "14",
    "매매가(만원)": 77145
  },
  {
    "계약월": "2009.05.",
    "계약일": "26",
    "층": "11",
    "매매가(만원)": 77145
  },
  {
    "계약월": "2009.05.",
    "계약일": "26",
    "층": "6",
    "매매가(만원)": 77145
  },
  {
    "계약월": "2009.05.",
    "계약일": "26",
    "층": "9",
    "매매가(만원)": 77145
  },
  {
    "계약월": "2009.05.",
    "계약일": "26",
    "층": "7",
    "매매가(만원)": 77145
  },
  {
    "계약월": "2009.05.",
    "계약일": "26",
    "층": "20",
    "매매가(만원)": 77145
  },
  {
    "계약월": "2009.05.",
    "계약일": "26",
    "층": "2",
    "매매가(만원)": 73353
  },
  {
    "계약월": "2009.05.",
    "계약일": "26",
    "층": "23",
    "매매가(만원)": 77145
  },
  {
    "계약월": "2009.05.",
    "계약일": "26",
    "층": "21",
    "매매가(만원)": 77145
  },
  {
    "계약월": "2009.05.",
    "계약일": "26",
    "층": "3",
    "매매가(만원)": 75225
  },
  {
    "계약월": "2009.05.",
    "계약일": "26",
    "층": "24",
    "매매가(만원)": 77145
  },
  {
    "계약월": "2009.05.",
    "계약일": "26",
    "층": "27",
    "매매가(만원)": 77145
  },
  {
    "계약월": "2009.05.",
    "계약일": "26",
    "층": "11",
    "매매가(만원)": 77532
  },
  {
    "계약월": "2009.05.",
    "계약일": "26",
    "층": "15",
    "매매가(만원)": 77532
  },
  {
    "계약월": "2009.05.",
    "계약일": "26",
    "층": "14",
    "매매가(만원)": 77532
  },
  {
    "계약월": "2009.05.",
    "계약일": "26",
    "층": "13",
    "매매가(만원)": 77532
  },
  {
    "계약월": "2009.05.",
    "계약일": "26",
    "층": "6",
    "매매가(만원)": 77532
  },
  {
    "계약월": "2009.05.",
    "계약일": "26",
    "층": "7",
    "매매가(만원)": 77532
  },
  {
    "계약월": "2009.05.",
    "계약일": "26",
    "층": "12",
    "매매가(만원)": 77145
  },
  {
    "계약월": "2009.05.",
    "계약일": "26",
    "층": "12",
    "매매가(만원)": 77532
  },
  {
    "계약월": "2009.05.",
    "계약일": "26",
    "층": "10",
    "매매가(만원)": 77532
  },
  {
    "계약월": "2009.05.",
    "계약일": "26",
    "층": "20",
    "매매가(만원)": 77532
  },
  {
    "계약월": "2009.05.",
    "계약일": "26",
    "층": "1",
    "매매가(만원)": 71157
  },
  {
    "계약월": "2009.05.",
    "계약일": "26",
    "층": "19",
    "매매가(만원)": 77532
  },
  {
    "계약월": "2009.05.",
    "계약일": "26",
    "층": "8",
    "매매가(만원)": 77532
  },
  {
    "계약월": "2009.05.",
    "계약일": "25",
    "층": "5",
    "매매가(만원)": 75225
  },
  {
    "계약월": "2009.05.",
    "계약일": "21",
    "층": "26",
    "매매가(만원)": 77145
  },
  {
    "계약월": "2009.05.",
    "계약일": "9",
    "층": "4",
    "매매가(만원)": 75225
  },
  {
    "계약월": "2009.05.",
    "계약일": "7",
    "층": "18",
    "매매가(만원)": 74500
  },
  {
    "계약월": "2009.05.",
    "계약일": "7",
    "층": "27",
    "매매가(만원)": 77532
  },
  {
    "계약월": "2009.05.",
    "계약일": "6",
    "층": "12",
    "매매가(만원)": 77532
  },
  {
    "계약월": "2009.05.",
    "계약일": "6",
    "층": "15",
    "매매가(만원)": 77532
  },
  {
    "계약월": "2009.05.",
    "계약일": "6",
    "층": "25",
    "매매가(만원)": 77532
  },
  {
    "계약월": "2009.05.",
    "계약일": "6",
    "층": "16",
    "매매가(만원)": 77532
  },
  {
    "계약월": "2009.05.",
    "계약일": "4",
    "층": "15",
    "매매가(만원)": 77145
  },
  {
    "계약월": "2009.05.",
    "계약일": "4",
    "층": "16",
    "매매가(만원)": 77532
  },
  {
    "계약월": "2009.05.",
    "계약일": "1",
    "층": "11",
    "매매가(만원)": 77145
  },
  {
    "계약월": "2009.05.",
    "계약일": "1",
    "층": "20",
    "매매가(만원)": 77145
  },
  {
    "계약월": "2009.04.",
    "계약일": "30",
    "층": "7",
    "매매가(만원)": 77145
  },
  {
    "계약월": "2009.04.",
    "계약일": "30",
    "층": "13",
    "매매가(만원)": 77145
  },
  {
    "계약월": "2009.04.",
    "계약일": "29",
    "층": "23",
    "매매가(만원)": 77532
  },
  {
    "계약월": "2009.04.",
    "계약일": "28",
    "층": "3",
    "매매가(만원)": 74850
  },
  {
    "계약월": "2009.04.",
    "계약일": "27",
    "층": "24",
    "매매가(만원)": 77532
  },
  {
    "계약월": "2009.04.",
    "계약일": "27",
    "층": "25",
    "매매가(만원)": 74800
  },
  {
    "계약월": "2009.04.",
    "계약일": "27",
    "층": "9",
    "매매가(만원)": 77145
  },
  {
    "계약월": "2009.04.",
    "계약일": "24",
    "층": "9",
    "매매가(만원)": 77145
  },
  {
    "계약월": "2009.04.",
    "계약일": "21",
    "층": "2",
    "매매가(만원)": 73353
  },
  {
    "계약월": "2009.04.",
    "계약일": "20",
    "층": "4",
    "매매가(만원)": 75225
  },
  {
    "계약월": "2009.04.",
    "계약일": "17",
    "층": "17",
    "매매가(만원)": 77532
  },
  {
    "계약월": "2009.04.",
    "계약일": "16",
    "층": "5",
    "매매가(만원)": 74850
  },
  {
    "계약월": "2009.04.",
    "계약일": "15",
    "층": "20",
    "매매가(만원)": 77532
  },
  {
    "계약월": "2009.04.",
    "계약일": "15",
    "층": "6",
    "매매가(만원)": 77145
  },
  {
    "계약월": "2009.04.",
    "계약일": "14",
    "층": "22",
    "매매가(만원)": 77532
  },
  {
    "계약월": "2009.04.",
    "계약일": "14",
    "층": "14",
    "매매가(만원)": 77532
  },
  {
    "계약월": "2009.04.",
    "계약일": "13",
    "층": "28",
    "매매가(만원)": 77532
  },
  {
    "계약월": "2009.04.",
    "계약일": "10",
    "층": "27",
    "매매가(만원)": 77532
  },
  {
    "계약월": "2009.04.",
    "계약일": "9",
    "층": "23",
    "매매가(만원)": 77532
  },
  {
    "계약월": "2009.04.",
    "계약일": "4",
    "층": "13",
    "매매가(만원)": 77145
  },
  {
    "계약월": "2009.04.",
    "계약일": "2",
    "층": "16",
    "매매가(만원)": 77532
  },
  {
    "계약월": "2009.04.",
    "계약일": "1",
    "층": "10",
    "매매가(만원)": 77145
  },
  {
    "계약월": "2009.03.",
    "계약일": "30",
    "층": "10",
    "매매가(만원)": 77532
  },
  {
    "계약월": "2009.03.",
    "계약일": "30",
    "층": "13",
    "매매가(만원)": 77532
  },
  {
    "계약월": "2009.03.",
    "계약일": "30",
    "층": "5",
    "매매가(만원)": 75225
  },
  {
    "계약월": "2009.03.",
    "계약일": "26",
    "층": "5",
    "매매가(만원)": 75225
  },
  {
    "계약월": "2009.03.",
    "계약일": "24",
    "층": "4",
    "매매가(만원)": 75225
  },
  {
    "계약월": "2009.03.",
    "계약일": "23",
    "층": "13",
    "매매가(만원)": 77145
  },
  {
    "계약월": "2009.03.",
    "계약일": "20",
    "층": "14",
    "매매가(만원)": 77145
  },
  {
    "계약월": "2009.03.",
    "계약일": "19",
    "층": "13",
    "매매가(만원)": 77145
  },
  {
    "계약월": "2009.03.",
    "계약일": "19",
    "층": "25",
    "매매가(만원)": 77532
  },
  {
    "계약월": "2009.03.",
    "계약일": "18",
    "층": "14",
    "매매가(만원)": 77145
  },
  {
    "계약월": "2009.03.",
    "계약일": "16",
    "층": "20",
    "매매가(만원)": 77145
  }
]